{
    "success": true,
    "data": [
        {
            "id": 1,
            "kategori_catatan": "Aturan Pemakaian",
            "catatan": "Durasi permainan maksimal 1 jam.",
            "urutan": 1,
            "is_active": true,
            "nama_lapangan": "Kencana Minisoccer"
        },
        {
            "id": 2,
            "kategori_catatan": "Aturan Pemakaian",
            "catatan": "Keterlambatan lebih dari 15 menit dari jadwal booking dianggap pembatalan.",
            "urutan": 2,
            "is_active": true,
            "nama_lapangan": "Kencana Minisoccer"
        },
        {
            "id": 3,
            "kategori_catatan": "Aturan Pemakaian",
            "catatan": "Dilarang membawa minuman keras dan zat adiktif lainnya.",
            "urutan": 3,
            "is_active": true,
            "nama_lapangan": "Kencana Minisoccer"
        },
        {
            "id": 4,
            "kategori_catatan": "Aturan Pemakaian",
            "catatan": "Dilarang merokok, meludah, makan permen karet, dan membuang sampah sembarangan di area lapangan.",
            "urutan": 4,
            "is_active": true,
            "nama_lapangan": "Kencana Minisoccer"
        },
        {
            "id": 5,
            "kategori_catatan": "Aturan Pemakaian",
            "catatan": "Dilarang merusak fasilitas lapangan dan wajib menjaga ketertiban selama penggunaan lapangan.",
            "urutan": 5,
            "is_active": true,
            "nama_lapangan": "Kencana Minisoccer"
        },
        {
            "id": 6,
            "kategori_catatan": "Aturan Pemakaian",
            "catatan": "Menghentikan aktivitas permainan saat tiba waktu shalat lima waktu.",
            "urutan": 6,
            "is_active": true,
            "nama_lapangan": "Kencana Minisoccer"
        },
        {
            "id": 7,
            "kategori_catatan": "Aturan Pemakaian",
            "catatan": "Menjaga kebersihan dan ketertiban selama berada di lokasi lapangan.",
            "urutan": 7,
            "is_active": true,
            "nama_lapangan": "Kencana Minisoccer"
        }
    ]
}
